Workbook

Sheet TechLayoffsTracker
A1: Nr | B1: Company | C1: Location_HQ | D1: Region | E1: USState | F1: Country | G1: Continent | H1: Laid_Off | I1: Date_layoffs | J1: Percentage | K1: Company_Size_before_Layoffs | L1: Company_Size_after_layoffs | M1: Industry | N1: Stage | O1: Money_Raised_in__mil | P1: Year | Q1: latitude | R1: longitude
A2: 1 | B2: Tamara Mellon | C2: Los Angeles | D2: =VLOOKUP(C2,layoffs_location!A:B,2,FALSE) -> other | E2: =VLOOKUP(C2,layoffs_location!A:C,3,FALSE) -> California | F2: =VLOOKUP(C2,layoffs_location!A:D,4,FALSE) -> USA | G2: =VLOOKUP(C2,layoffs_location!A:E,5,FALSE) -> North America | H2: 20 | I2: 43902 | J2: 40 | K2: 50 | L2: 30 | M2: Retail | N2: Series C | O2: 90 | P2: 2020 | Q2: =VLOOKUP(C2,layoffs_location!A:F,6,FALSE) -> 34.053691 | R2: =VLOOKUP(C2,layoffs_location!A:G,7,FALSE) -> -118.24277
A3: 2 | B3: HopSkipDrive | C3: Los Angeles | D3: =VLOOKUP(C3,layoffs_location!A:B,2,FALSE) -> other | E3: =VLOOKUP(C3,layoffs_location!A:C,3,FALSE) -> California | F3: =VLOOKUP(C3,layoffs_location!A:D,4,FALSE) -> USA | G3: =VLOOKUP(C3,layoffs_location!A:E,5,FALSE) -> North America | H3: 8 | I3: 43903 | J3: 10 | K3: 80 | L3: 72 | M3: Transportation | N3: Unknown | O3: 45 | P3: 2020 | Q3: =VLOOKUP(C3,layoffs_location!A:F,6,FALSE) -> 34.053691 | R3: =VLOOKUP(C3,layoffs_location!A:G,7,FALSE) -> -118.24277
A4: 3 | B4: Panda Squad | C4: San Francisco | D4: =VLOOKUP(C4,layoffs_location!A:B,2,FALSE) -> San Francisco Bay Area | E4: =VLOOKUP(C4,layoffs_location!A:C,3,FALSE) -> California | F4: =VLOOKUP(C4,layoffs_location!A:D,4,FALSE) -> USA | G4: =VLOOKUP(C4,layoffs_location!A:E,5,FALSE) -> North America | H4: 6 | I4: 43903 | J4: 75 | K4: 8 | L4: 2 | M4: Consumer | N4: Seed | O4: 1 | P4: 2020 | Q4: =VLOOKUP(C4,layoffs_location!A:F,6,FALSE) -> 37.779259 | R4: =VLOOKUP(C4,layoffs_location!A:G,7,FALSE) -> -122.41933
A5: 4 | B5: Help.com | C5: Austin | D5: =VLOOKUP(C5,layoffs_location!A:B,2,FALSE) -> other | E5: =VLOOKUP(C5,layoffs_location!A:C,3,FALSE) -> Texas | F5: =VLOOKUP(C5,layoffs_location!A:D,4,FALSE) -> USA | G5: =VLOOKUP(C5,layoffs_location!A:E,5,FALSE) -> North America | H5: 16 | I5: 43906 | J5: 100 | K5: 16 | L5: 0 | M5: Support | N5: Seed | O5: 6 | P5: 2020 | Q5: =VLOOKUP(C5,layoffs_location!A:F,6,FALSE) -> 30.271129 | R5: =VLOOKUP(C5,layoffs_location!A:G,7,FALSE) -> -97.7437
A6: 5 | B6: Inspirato | C6: Denver | D6: =VLOOKUP(C6,layoffs_location!A:B,2,FALSE) -> other | E6: =VLOOKUP(C6,layoffs_location!A:C,3,FALSE) -> Colorado | F6: =VLOOKUP(C6,layoffs_location!A:D,4,FALSE) -> USA | G6: =VLOOKUP(C6,layoffs_location!A:E,5,FALSE) -> North America | H6: 130 | I6: 43906 | J6: 22 | K6: 591 | L6: 461 | M6: Travel | N6: Series C | O6: 79 | P6: 2020 | Q6: =VLOOKUP(C6,layoffs_location!A:F,6,FALSE) -> 39.739236 | R6: =VLOOKUP(C6,layoffs_location!A:G,7,FALSE) -> -104.98486
A7: 6 | B7: Flytedesk | C7: Boulder | D7: =VLOOKUP(C7,layoffs_location!A:B,2,FALSE) -> other | E7: =VLOOKUP(C7,layoffs_location!A:C,3,FALSE) -> Colorado | F7: =VLOOKUP(C7,layoffs_location!A:D,4,FALSE) -> USA | G7: =VLOOKUP(C7,layoffs_location!A:E,5,FALSE) -> North America | H7: 4 | I7: 43908 | J7: 20 | K7: 20 | L7: 16 | M7: Marketing | N7: Seed | O7: 4 | P7: 2020 | Q7: =VLOOKUP(C7,layoffs_location!A:F,6,FALSE) -> 40.014986 | R7: =VLOOKUP(C7,layoffs_location!A:G,7,FALSE) -> -105.27054
A8: 7 | B8: Remote Year | C8: Chicago | D8: =VLOOKUP(C8,layoffs_location!A:B,2,FALSE) -> other | E8: =VLOOKUP(C8,layoffs_location!A:C,3,FALSE) -> Illinois | F8: =VLOOKUP(C8,layoffs_location!A:D,4,FALSE) -> USA | G8: =VLOOKUP(C8,layoffs_location!A:E,5,FALSE) -> North America | H8: 50 | I8: 43909 | J8: 50 | K8: 100 | L8: 50 | M8: Travel | N8: Series B | O8: 17 | P8: 2020 | Q8: =VLOOKUP(C8,layoffs_location!A:F,6,FALSE) -> 41.875562 | R8: =VLOOKUP(C8,layoffs_location!A:G,7,FALSE) -> -87.624421
A9: 8 | B9: CTO.ai | C9: Vancouver | D9: =VLOOKUP(C9,layoffs_location!A:B,2,FALSE) -> Cascadia | E9: =VLOOKUP(C9,layoffs_location!A:C,3,FALSE) -> British Columbia | F9: =VLOOKUP(C9,layoffs_location!A:D,4,FALSE) -> Canada | G9: =VLOOKUP(C9,layoffs_location!A:E,5,FALSE) -> North America | H9: 30 | I9: 43910 | J9: 50 | K9: 60 | L9: 30 | M9: Infrastructure | N9: Seed | O9: 7 | P9: 2020 | Q9: =VLOOKUP(C9,layoffs_location!A:F,6,FALSE) -> 49.260872 | R9: =VLOOKUP(C9,layoffs_location!A:G,7,FALSE) -> -123.11395
A10: 9 | B10: Flywheel Sports | C10: New York City | D10: =VLOOKUP(C10,layoffs_location!A:B,2,FALSE) -> New York | E10: =VLOOKUP(C10,layoffs_location!A:C,3,FALSE) -> New York | F10: =VLOOKUP(C10,layoffs_location!A:D,4,FALSE) -> USA | G10: =VLOOKUP(C10,layoffs_location!A:E,5,FALSE) -> North America | H10: 784 | I10: 43910 | J10: 98 | K10: 800 | L10: 16 | M10: Fitness | N10: Acquired | O10: 120 | P10: 2020 | Q10: =VLOOKUP(C10,layoffs_location!A:F,6,FALSE) -> 40.712728 | R10: =VLOOKUP(C10,layoffs_location!A:G,7,FALSE) -> -74.006015
A11: 10 | B11: Compass | C11: New York City | D11: =VLOOKUP(C11,layoffs_location!A:B,2,FALSE) -> New York | E11: =VLOOKUP(C11,layoffs_location!A:C,3,FALSE) -> New York | F11: =VLOOKUP(C11,layoffs_location!A:D,4,FALSE) -> USA | G11: =VLOOKUP(C11,layoffs_location!A:E,5,FALSE) -> North America | H11: 375 | I11: 43913 | J11: 15 | K11: 2500 | L11: 2125 | M11: Real Estate | N11: Series G | O11: 1600 | P11: 2020 | Q11: =VLOOKUP(C11,layoffs_location!A:F,6,FALSE) -> 40.712728 | R11: =VLOOKUP(C11,layoffs_location!A:G,7,FALSE) -> -74.006015
A12: 11 | B12: Convene | C12: New York City | D12: =VLOOKUP(C12,layoffs_location!A:B,2,FALSE) -> New York | E12: =VLOOKUP(C12,layoffs_location!A:C,3,FALSE) -> New York | F12: =VLOOKUP(C12,layoffs_location!A:D,4,FALSE) -> USA | G12: =VLOOKUP(C12,layoffs_location!A:E,5,FALSE) -> North America | H12: 150 | I12: 43913 | J12: 18 | K12: 833 | L12: 683 | M12: Real Estate | N12: Series D | O12: 280 | P12: 2020 | Q12: =VLOOKUP(C12,layoffs_location!A:F,6,FALSE) -> 40.712728 | R12: =VLOOKUP(C12,layoffs_location!A:G,7,FALSE) -> -74.006015
A13: 12 | B13: GrayMeta | C13: Los Angeles | D13: =VLOOKUP(C13,layoffs_location!A:B,2,FALSE) -> other | E13: =VLOOKUP(C13,layoffs_location!A:C,3,FALSE) -> California | F13: =VLOOKUP(C13,layoffs_location!A:D,4,FALSE) -> USA | G13: =VLOOKUP(C13,layoffs_location!A:E,5,FALSE) -> North America | H13: 20 | I13: 43913 | J13: 40 | K13: 50 | L13: 30 | M13: Data | N13: Unknown | O13: 7 | P13: 2020 | Q13: =VLOOKUP(C13,layoffs_location!A:F,6,FALSE) -> 34.053691 | R13: =VLOOKUP(C13,layoffs_location!A:G,7,FALSE) -> -118.24277
... A23: 22 | B23: Overtime | C23: New York City | D23: =VLOOKUP(C23,layoffs_location!A:B,2,FALSE) -> New York | E23: =VLOOKUP(C23,layoffs_location!A:C,3,FALSE) -> New York | F23: =VLOOKUP(C23,layoffs_location!A:D,4,FALSE) -> USA | G23: =VLOOKUP(C23,layoffs_location!A:E,5,FALSE) -> North America | H23: 30 | I23: 43915 | J23: 23 | K23: 130 | L23: 100 | M23: Media | N23: Series B | O23: 35 | P23: 2020 | Q23: =VLOOKUP(C23,layoffs_location!A:F,6,FALSE) -> 40.712728 | R23: =VLOOKUP(C23,layoffs_location!A:G,7,FALSE) -> -74.006015
A24: 23 | B24: TripActions | C24: Palo Alto | D24: =VLOOKUP(C24,layoffs_location!A:B,2,FALSE) -> San Francisco Bay Area | E24: =VLOOKUP(C24,layoffs_location!A:C,3,FALSE) -> California | F24: =VLOOKUP(C24,layoffs_location!A:D,4,FALSE) -> USA | G24: =VLOOKUP(C24,layoffs_location!A:E,5,FALSE) -> North America | H24: 300 | I24: 43915 | J24: 25 | K24: 1200 | L24: 900 | M24: Travel | N24: Series D | P24: 2020 | Q24: =VLOOKUP(C24,layoffs_location!A:F,6,FALSE) -> 37.444329 | R24: =VLOOKUP(C24,layoffs_location!A:G,7,FALSE) -> -122.15985
A25: 24 | B25: WanderJaunt | C25: San Francisco | D25: =VLOOKUP(C25,layoffs_location!A:B,2,FALSE) -> San Francisco Bay Area | E25: =VLOOKUP(C25,layoffs_location!A:C,3,FALSE) -> California | F25: =VLOOKUP(C25,layoffs_location!A:D,4,FALSE) -> USA | G25: =VLOOKUP(C25,layoffs_location!A:E,5,FALSE) -> North America | H25: 56 | I25: 43915 | J25: 23 | K25: 243 | L25: 187 | M25: Travel | N25: Series B | O25: 26 | P25: 2020 | Q25: =VLOOKUP(C25,layoffs_location!A:F,6,FALSE) -> 37.779259 | R25: =VLOOKUP(C25,layoffs_location!A:G,7,FALSE) -> -122.41933
A26: 25 | B26: Wonderschool | C26: San Francisco | D26: =VLOOKUP(C26,layoffs_location!A:B,2,FALSE) -> San Francisco Bay Area | E26: =VLOOKUP(C26,layoffs_location!A:C,3,FALSE) -> California | F26: =VLOOKUP(C26,layoffs_location!A:D,4,FALSE) -> USA | G26: =VLOOKUP(C26,layoffs_location!A:E,5,FALSE) -> North America | H26: 50 | I26: 43915 | J26: 75 | K26: 67 | L26: 17 | M26: Education | N26: Series A | O26: 24 | P26: 2020 | Q26: =VLOOKUP(C26,layoffs_location!A:F,6,FALSE) -> 37.779259 | R26: =VLOOKUP(C26,layoffs_location!A:G,7,FALSE) -> -122.41933
A27: 26 | B27: B8ta | C27: San Francisco | D27: =VLOOKUP(C27,layoffs_location!A:B,2,FALSE) -> San Francisco Bay Area | E27: =VLOOKUP(C27,layoffs_location!A:C,3,FALSE) -> California | F27: =VLOOKUP(C27,layoffs_location!A:D,4,FALSE) -> USA | G27: =VLOOKUP(C27,layoffs_location!A:E,5,FALSE) -> North America | H27: 250 | I27: 43916 | J27: 50 | K27: 500 | L27: 250 | M27: Retail | N27: Series C | O27: 88 | P27: 2020 | Q27: =VLOOKUP(C27,layoffs_location!A:F,6,FALSE) -> 37.779259 | R27: =VLOOKUP(C27,layoffs_location!A:G,7,FALSE) -> -122.41933
A28: 27 | B28: Consider.co | C28: Mountain View | D28: =VLOOKUP(C28,layoffs_location!A:B,2,FALSE) -> San Francisco Bay Area | E28: =VLOOKUP(C28,layoffs_location!A:C,3,FALSE) -> California | F28: =VLOOKUP(C28,layoffs_location!A:D,4,FALSE) -> USA | G28: =VLOOKUP(C28,layoffs_location!A:E,5,FALSE) -> North America | H28: 13 | I28: 43916 | J28: 100 | K28: 13 | L28: 0 | M28: Other | N28: Seed | O28: 5 | P28: 2020 | Q28: =VLOOKUP(C28,layoffs_location!A:F,6,FALSE) -> 37.389389 | R28: =VLOOKUP(C28,layoffs_location!A:G,7,FALSE) -> -122.08321
A29: 28 | B29: Ecobee | C29: Toronto | D29: =VLOOKUP(C29,layoffs_location!A:B,2,FALSE) -> other | E29: =VLOOKUP(C29,layoffs_location!A:C,3,FALSE) -> Ontario | F29: =VLOOKUP(C29,layoffs_location!A:D,4,FALSE) -> Canada | G29: =VLOOKUP(C29,layoffs_location!A:E,5,FALSE) -> North America | H29: 47 | I29: 43916 | J29: 10 | K29: 470 | L29: 423 | M29: Energy | N29: Series C | O29: 149 | P29: 2020 | Q29: =VLOOKUP(C29,layoffs_location!A:F,6,FALSE) -> 43.653482 | R29: =VLOOKUP(C29,layoffs_location!A:G,7,FALSE) -> -79.383935
A30: 29 | B30: GoSpotCheck | C30: Denver | D30: =VLOOKUP(C30,layoffs_location!A:B,2,FALSE) -> other | E30: =VLOOKUP(C30,layoffs_location!A:C,3,FALSE) -> Colorado | F30: =VLOOKUP(C30,layoffs_location!A:D,4,FALSE) -> USA | G30: =VLOOKUP(C30,layoffs_location!A:E,5,FALSE) -> North America | H30: 23 | I30: 43916 | J30: 20 | K30: 115 | L30: 92 | M30: Retail | N30: Series B | O30: 47 | P30: 2020 | Q30: =VLOOKUP(C30,layoffs_location!A:F,6,FALSE) -> 39.739236 | R30: =VLOOKUP(C30,layoffs_location!A:G,7,FALSE) -> -104.98486
A31: 30 | B31: Peerspace | C31: San Francisco | D31: =VLOOKUP(C31,layoffs_location!A:B,2,FALSE) -> San Francisco Bay Area | E31: =VLOOKUP(C31,layoffs_location!A:C,3,FALSE) -> California | F31: =VLOOKUP(C31,layoffs_location!A:D,4,FALSE) -> USA | G31: =VLOOKUP(C31,layoffs_location!A:E,5,FALSE) -> North America | H31: 41 | I31: 43916 | J31: 75 | K31: 55 | L31: 14 | M31: Real Estate | N31: Series B | O31: 34 | P31: 2020 | Q31: =VLOOKUP(C31,layoffs_location!A:F,6,FALSE) -> 37.779259 | R31: =VLOOKUP(C31,layoffs_location!A:G,7,FALSE) -> -122.41933
A32: 31 | B32: Puppet | C32: Portland | D32: =VLOOKUP(C32,layoffs_location!A:B,2,FALSE) -> Cascadia | E32: =VLOOKUP(C32,layoffs_location!A:C,3,FALSE) -> Oregon | F32: =VLOOKUP(C32,layoffs_location!A:D,4,FALSE) -> USA | G32: =VLOOKUP(C32,layoffs_location!A:E,5,FALSE) -> North America | H32: 50 | I32: 43916 | J32: 10 | K32: 500 | L32: 450 | M32: Infrastructure | N32: Series F | O32: 149 | P32: 2020 | Q32: =VLOOKUP(C32,layoffs_location!A:F,6,FALSE) -> 45.520247 | R32: =VLOOKUP(C32,layoffs_location!A:G,7,FALSE) -> -122.67419
A33: 32 | B33: Bench | C33: Vancouver | D33: =VLOOKUP(C33,layoffs_location!A:B,2,FALSE) -> Cascadia | E33: =VLOOKUP(C33,layoffs_location!A:C,3,FALSE) -> British Columbia | F33: =VLOOKUP(C33,layoffs_location!A:D,4,FALSE) -> Canada | G33: =VLOOKUP(C33,layoffs_location!A:E,5,FALSE) -> North America | H33: 47 | I33: 43917 | J33: 10 | K33: 470 | L33: 423 | M33: Finance | N33: Series B | O33: 49 | P33: 2020 | Q33: =VLOOKUP(C33,layoffs_location!A:F,6,FALSE) -> 49.260872 | R33: =VLOOKUP(C33,layoffs_location!A:G,7,FALSE) -> -123.11395
A34: 33 | B34: Bevi | C34: Boston | D34: =VLOOKUP(C34,layoffs_location!A:B,2,FALSE) -> other | E34: =VLOOKUP(C34,layoffs_location!A:C,3,FALSE) -> Massachusetts | F34: =VLOOKUP(C34,layoffs_location!A:D,4,FALSE) -> USA | G34: =VLOOKUP(C34,layoffs_location!A:E,5,FALSE) -> North America | H34: 30 | I34: 43917 | J34: 20 | K34: 150 | L34: 120 | M34: Food | N34: Series C | O34: 60 | P34: 2020 | Q34: =VLOOKUP(C34,layoffs_location!A:F,6,FALSE) -> 42.355433 | R34: =VLOOKUP(C34,layoffs_location!A:G,7,FALSE) -> -71.060511
A35: 34 | B35: Bird | C35: Los Angeles | D35: =VLOOKUP(C35,layoffs_location!A:B,2,FALSE) -> other | E35: =VLOOKUP(C35,layoffs_location!A:C,3,FALSE) -> California | F35: =VLOOKUP(C35,layoffs_location!A:D,4,FALSE) -> USA | G35: =VLOOKUP(C35,layoffs_location!A:E,5,FALSE) -> North America | H35: 406 | I35: 43917 | J35: 30 | K35: 1353 | L35: 947 | M35: Transportation | N35: Series D | O35: 623 | P35: 2020 | Q35: =VLOOKUP(C35,layoffs_location!A:F,6,FALSE) -> 34.053691 | R35: =VLOOKUP(C35,layoffs_location!A:G,7,FALSE) -> -118.24277
A36: 35 | B36: Blueground | C36: New York City | D36: =VLOOKUP(C36,layoffs_location!A:B,2,FALSE) -> New York | E36: =VLOOKUP(C36,layoffs_location!A:C,3,FALSE) -> New York | F36: =VLOOKUP(C36,layoffs_location!A:D,4,FALSE) -> USA | G36: =VLOOKUP(C36,layoffs_location!A:E,5,FALSE) -> North America | H36: 130 | I36: 43917 | J36: 25 | K36: 520 | L36: 390 | M36: Real Estate | N36: Series B | O36: 77 | P36: 2020 | Q36: =VLOOKUP(C36,layoffs_location!A:F,6,FALSE) -> 40.712728 | R36: =VLOOKUP(C36,layoffs_location!A:G,7,FALSE) -> -74.006015
... A41: 40 | B41: Mogo | C41: Vancouver | D41: =VLOOKUP(C41,layoffs_location!A:B,2,FALSE) -> Cascadia | E41: =VLOOKUP(C41,layoffs_location!A:C,3,FALSE) -> British Columbia | F41: =VLOOKUP(C41,layoffs_location!A:D,4,FALSE) -> Canada | G41: =VLOOKUP(C41,layoffs_location!A:E,5,FALSE) -> North America | H41: 78 | I41: 43917 | J41: 30 | K41: 260 | L41: 182 | M41: Finance | N41: Post-IPO | O41: 201 | P41: 2020 | Q41: =VLOOKUP(C41,layoffs_location!A:F,6,FALSE) -> 49.260872 | R41: =VLOOKUP(C41,layoffs_location!A:G,7,FALSE) -> -123.11395
A42: 41 | B42: OneWeb | C42: London | D42: =VLOOKUP(C42,layoffs_location!A:B,2,FALSE) -> other | E42: =VLOOKUP(C42,layoffs_location!A:C,3,FALSE) -> England | F42: =VLOOKUP(C42,layoffs_location!A:D,4,FALSE) -> UK | G42: =VLOOKUP(C42,layoffs_location!A:E,5,FALSE) -> Europe | H42: 451 | I42: 43917 | J42: 85 | K42: 531 | L42: 80 | M42: Aerospace | N42: Unknown | P42: 2020 | Q42: =VLOOKUP(C42,layoffs_location!A:F,6,FALSE) -> 51.489334 | R42: =VLOOKUP(C42,layoffs_location!A:G,7,FALSE) -> -0.14405508
A43: 42 | B43: Textio | C43: Seattle | D43: =VLOOKUP(C43,layoffs_location!A:B,2,FALSE) -> Cascadia | E43: =VLOOKUP(C43,layoffs_location!A:C,3,FALSE) -> Washington | F43: =VLOOKUP(C43,layoffs_location!A:D,4,FALSE) -> USA | G43: =VLOOKUP(C43,layoffs_location!A:E,5,FALSE) -> North America | H43: 30 | I43: 43917 | J43: 20 | K43: 150 | L43: 120 | M43: HR | N43: Unknown | O43: 41 | P43: 2020 | Q43: =VLOOKUP(C43,layoffs_location!A:F,6,FALSE) -> 47.603832 | R43: =VLOOKUP(C43,layoffs_location!A:G,7,FALSE) -> -122.33006
A44: 43 | B44: Zipcar | C44: Boston | D44: =VLOOKUP(C44,layoffs_location!A:B,2,FALSE) -> other | E44: =VLOOKUP(C44,layoffs_location!A:C,3,FALSE) -> Massachusetts | F44: =VLOOKUP(C44,layoffs_location!A:D,4,FALSE) -> USA | G44: =VLOOKUP(C44,layoffs_location!A:E,5,FALSE) -> North America | H44: 100 | I44: 43917 | J44: 20 | K44: 500 | L44: 400 | M44: Transportation | N44: Acquired | O44: 107 | P44: 2020 | Q44: =VLOOKUP(C44,layoffs_location!A:F,6,FALSE) -> 42.355433 | R44: =VLOOKUP(C44,layoffs_location!A:G,7,FALSE) -> -71.060511
A45: 44 | B45: TravelTriangle | C45: Gurugram | D45: =VLOOKUP(C45,layoffs_location!A:B,2,FALSE) -> other | E45: =VLOOKUP(C45,layoffs_location!A:C,3,FALSE) -> Haryana | F45: =VLOOKUP(C45,layoffs_location!A:D,4,FALSE) -> India | G45: =VLOOKUP(C45,layoffs_location!A:E,5,FALSE) -> Asia | H45: 250 | I45: 43918 | J45: 50 | K45: 500 | L45: 250 | M45: Travel | N45: Series D | O45: 47 | P45: 2020 | Q45: =VLOOKUP(C45,layoffs_location!A:F,6,FALSE) -> 28.464615 | R45: =VLOOKUP(C45,layoffs_location!A:G,7,FALSE) -> 77.029919
A46: 45 | B46: Amplero | C46: Seattle | D46: =VLOOKUP(C46,layoffs_location!A:B,2,FALSE) -> Cascadia | E46: =VLOOKUP(C46,layoffs_location!A:C,3,FALSE) -> Washington | F46: =VLOOKUP(C46,layoffs_location!A:D,4,FALSE) -> USA | G46: =VLOOKUP(C46,layoffs_location!A:E,5,FALSE) -> North America | H46: 17 | I46: 43919 | J46: 100 | K46: 17 | L46: 0 | M46: Marketing | N46: Series B | O46: 25 | P46: 2020 | Q46: =VLOOKUP(C46,layoffs_location!A:F,6,FALSE) -> 47.603832 | R46: =VLOOKUP(C46,layoffs_location!A:G,7,FALSE) -> -122.33006
A47: 46 | B47: ZipRecruiter | C47: Los Angeles | D47: =VLOOKUP(C47,layoffs_location!A:B,2,FALSE) -> other | E47: =VLOOKUP(C47,layoffs_location!A:C,3,FALSE) -> California | F47: =VLOOKUP(C47,layoffs_location!A:D,4,FALSE) -> USA | G47: =VLOOKUP(C47,layoffs_location!A:E,5,FALSE) -> North America | H47: 400 | I47: 43919 | J47: 39 | K47: 1026 | L47: 626 | M47: HR | N47: Series B | O47: 219 | P47: 2020 | Q47: =VLOOKUP(C47,layoffs_location!A:F,6,FALSE) -> 34.053691 | R47: =VLOOKUP(C47,layoffs_location!A:G,7,FALSE) -> -118.24277
A48: 47 | B48: FabHotels | C48: New Delhi | D48: =VLOOKUP(C48,layoffs_location!A:B,2,FALSE) -> other | E48: =VLOOKUP(C48,layoffs_location!A:C,3,FALSE) -> Delhi | F48: =VLOOKUP(C48,layoffs_location!A:D,4,FALSE) -> India | G48: =VLOOKUP(C48,layoffs_location!A:E,5,FALSE) -> Asia | H48: 80 | I48: 43920 | J48: 20 | K48: 400 | L48: 320 | M48: Travel | N48: Series B | O48: 48 | P48: 2020 | Q48: =VLOOKUP(C48,layoffs_location!A:F,6,FALSE) -> 28.613895 | R48: =VLOOKUP(C48,layoffs_location!A:G,7,FALSE) -> 77.209006
A49: 48 | B49: Hibob | C49: Tel Aviv | D49: =VLOOKUP(C49,layoffs_location!A:B,2,FALSE) -> other | E49: =VLOOKUP(C49,layoffs_location!A:C,3,FALSE) -> non | F49: =VLOOKUP(C49,layoffs_location!A:D,4,FALSE) -> Israel | G49: =VLOOKUP(C49,layoffs_location!A:E,5,FALSE) -> Asia | H49: 70 | I49: 43920 | J49: 30 | K49: 233 | L49: 163 | M49: HR | N49: Series A | O49: 45 | P49: 2020 | Q49: =VLOOKUP(C49,layoffs_location!A:F,6,FALSE) -> 32.0853 | R49: =VLOOKUP(C49,layoffs_location!A:G,7,FALSE) -> 34.781806
A50: 49 | B50: Iris Nova | C50: New York City | D50: =VLOOKUP(C50,layoffs_location!A:B,2,FALSE) -> New York | E50: =VLOOKUP(C50,layoffs_location!A:C,3,FALSE) -> New York | F50: =VLOOKUP(C50,layoffs_location!A:D,4,FALSE) -> USA | G50: =VLOOKUP(C50,layoffs_location!A:E,5,FALSE) -> North America | H50: 9 | I50: 43920 | J50: 50 | K50: 18 | L50: 9 | M50: Food | N50: Seed | O50: 15 | P50: 2020 | Q50: =VLOOKUP(C50,layoffs_location!A:F,6,FALSE) -> 40.712728 | R50: =VLOOKUP(C50,layoffs_location!A:G,7,FALSE) -> -74.006015
A51: 50 | B51: Loftsmart | C51: New York City | D51: =VLOOKUP(C51,layoffs_location!A:B,2,FALSE) -> New York | E51: =VLOOKUP(C51,layoffs_location!A:C,3,FALSE) -> New York | F51: =VLOOKUP(C51,layoffs_location!A:D,4,FALSE) -> USA | G51: =VLOOKUP(C51,layoffs_location!A:E,5,FALSE) -> North America | H51: 25 | I51: 43920 | J51: 75 | K51: 33 | L51: 8 | M51: Real Estate | N51: Series A | O51: 18 | P51: 2020 | Q51: =VLOOKUP(C51,layoffs_location!A:F,6,FALSE) -> 40.712728 | R51: =VLOOKUP(C51,layoffs_location!A:G,7,FALSE) -> -74.006015
A52: 51 | B52: Maven | C52: Seattle | D52: =VLOOKUP(C52,layoffs_location!A:B,2,FALSE) -> Cascadia | E52: =VLOOKUP(C52,layoffs_location!A:C,3,FALSE) -> Washington | F52: =VLOOKUP(C52,layoffs_location!A:D,4,FALSE) -> USA | G52: =VLOOKUP(C52,layoffs_location!A:E,5,FALSE) -> North America | H52: 31 | I52: 43920 | J52: 9 | K52: 344 | L52: 313 | M52: Media | N52: Post-IPO | O52: 77 | P52: 2020 | Q52: =VLOOKUP(C52,layoffs_location!A:F,6,FALSE) -> 47.603832 | R52: =VLOOKUP(C52,layoffs_location!A:G,7,FALSE) -> -122.33006
A53: 52 | B53: PeerStreet | C53: Los Angeles | D53: =VLOOKUP(C53,layoffs_location!A:B,2,FALSE) -> other | E53: =VLOOKUP(C53,layoffs_location!A:C,3,FALSE) -> California | F53: =VLOOKUP(C53,layoffs_location!A:D,4,FALSE) -> USA | G53: =VLOOKUP(C53,layoffs_location!A:E,5,FALSE) -> North America | H53: 51 | I53: 43920 | J53: 30 | K53: 170 | L53: 119 | M53: Finance | N53: Series C | O53: 110 | P53: 2020 | Q53: =VLOOKUP(C53,layoffs_location!A:F,6,FALSE) -> 34.053691 | R53: =VLOOKUP(C53,layoffs_location!A:G,7,FALSE) -> -118.24277
A54: 53 | B54: RigUp | C54: Austin | D54: =VLOOKUP(C54,layoffs_location!A:B,2,FALSE) -> other | E54: =VLOOKUP(C54,layoffs_location!A:C,3,FALSE) -> Texas | F54: =VLOOKUP(C54,layoffs_location!A:D,4,FALSE) -> USA | G54: =VLOOKUP(C54,layoffs_location!A:E,5,FALSE) -> North America | H54: 120 | I54: 43920 | J54: 25 | K54: 480 | L54: 360 | M54: Energy | N54: Series D | O54: 423 | P54: 2020 | Q54: =VLOOKUP(C54,layoffs_location!A:F,6,FALSE) -> 30.271129 | R54: =VLOOKUP(C54,layoffs_location!A:G,7,FALSE) -> -97.7437
... A145: 144 | B145: EasyPost | C145: San Francisco | D145: =VLOOKUP(C145,layoffs_location!A:B,2,FALSE) -> San Francisco Bay Area | E145: =VLOOKUP(C145,layoffs_location!A:C,3,FALSE) -> California | F145: =VLOOKUP(C145,layoffs_location!A:D,4,FALSE) -> USA | G145: =VLOOKUP(C145,layoffs_location!A:E,5,FALSE) -> North America | H145: 50 | I145: 43934 | J145: 25 | K145: 200 | L145: 150 | M145: Logistics | N145: Series A | O145: 12 | P145: 2020 | Q145: =VLOOKUP(C145,layoffs_location!A:F,6,FALSE) -> 37.779259 | R145: =VLOOKUP(C145,layoffs_location!A:G,7,FALSE) -> -122.41933
A146: 145 | B146: Groupon | C146: Chicago | D146: =VLOOKUP(C146,layoffs_location!A:B,2,FALSE) -> other | E146: =VLOOKUP(C146,layoffs_location!A:C,3,FALSE) -> Illinois | F146: =VLOOKUP(C146,layoffs_location!A:D,4,FALSE) -> USA | G146: =VLOOKUP(C146,layoffs_location!A:E,5,FALSE) -> North America | H146: 2800 | I146: 43934 | J146: 44 | K146: 6364 | L146: 3564 | M146: Retail | N146: Post-IPO | P146: 2020 | Q146: =VLOOKUP(C146,layoffs_location!A:F,6,FALSE) -> 41.875562 | R146: =VLOOKUP(C146,layoffs_location!A:G,7,FALSE) -> -87.624421
A147: 146 | B147: Neon | C147: Sao Paulo | D147: =VLOOKUP(C147,layoffs_location!A:B,2,FALSE) -> other | E147: =VLOOKUP(C147,layoffs_location!A:C,3,FALSE) -> State of São Paulo | F147: =VLOOKUP(C147,layoffs_location!A:D,4,FALSE) -> Brazil | G147: =VLOOKUP(C147,layoffs_location!A:E,5,FALSE) -> South America | H147: 70 | I147: 43934 | J147: 10 | K147: 700 | L147: 630 | M147: Finance | N147: Series B | O147: 120 | P147: 2020 | Q147: =VLOOKUP(C147,layoffs_location!A:F,6,FALSE) -> -23.550651 | R147: =VLOOKUP(C147,layoffs_location!A:G,7,FALSE) -> -46.633382
A148: 147 | B148: Zoox | C148: Forster City | D148: =VLOOKUP(C148,layoffs_location!A:B,2,FALSE) -> San Francisco Bay Area | E148: =VLOOKUP(C148,layoffs_location!A:C,3,FALSE) -> California | F148: =VLOOKUP(C148,layoffs_location!A:D,4,FALSE) -> USA | G148: =VLOOKUP(C148,layoffs_location!A:E,5,FALSE) -> North America | H148: 100 | I148: 43934 | J148: 10 | K148: 1000 | L148: 900 | M148: Transportation | N148: Series B | O148: 955 | P148: 2020 | Q148: =VLOOKUP(C148,layoffs_location!A:F,6,FALSE) -> 37.558546 | R148: =VLOOKUP(C148,layoffs_location!A:G,7,FALSE) -> -122.27108
A149: 148 | B149: Envoy | C149: San Francisco | D149: =VLOOKUP(C149,layoffs_location!A:B,2,FALSE) -> San Francisco Bay Area | E149: =VLOOKUP(C149,layoffs_location!A:C,3,FALSE) -> California | F149: =VLOOKUP(C149,layoffs_location!A:D,4,FALSE) -> USA | G149: =VLOOKUP(C149,layoffs_location!A:E,5,FALSE) -> North America | H149: 58 | I149: 43935 | J149: 30 | K149: 193 | L149: 135 | M149: HR | N149: Series B | O149: 59 | P149: 2020 | Q149: =VLOOKUP(C149,layoffs_location!A:F,6,FALSE) -> 37.779259 | R149: =VLOOKUP(C149,layoffs_location!A:G,7,FALSE) -> -122.41933
A150: 149 | B150: The RealReal | C150: San Francisco | D150: =VLOOKUP(C150,layoffs_location!A:B,2,FALSE) -> San Francisco Bay Area | E150: =VLOOKUP(C150,layoffs_location!A:C,3,FALSE) -> California | F150: =VLOOKUP(C150,layoffs_location!A:D,4,FALSE) -> USA | G150: =VLOOKUP(C150,layoffs_location!A:E,5,FALSE) -> North America | H150: 235 | I150: 43935 | J150: 10 | K150: 2350 | L150: 2115 | M150: Retail | N150: Post-IPO | O150: 358 | P150: 2020 | Q150: =VLOOKUP(C150,layoffs_location!A:F,6,FALSE) -> 37.779259 | R150: =VLOOKUP(C150,layoffs_location!A:G,7,FALSE) -> -122.41933
A151: 150 | B151: TouchBistro | C151: Toronto | D151: =VLOOKUP(C151,layoffs_location!A:B,2,FALSE) -> other | E151: =VLOOKUP(C151,layoffs_location!A:C,3,FALSE) -> Ontario | F151: =VLOOKUP(C151,layoffs_location!A:D,4,FALSE) -> Canada | G151: =VLOOKUP(C151,layoffs_location!A:E,5,FALSE) -> North America | H151: 131 | I151: 43935 | J151: 23 | K151: 570 | L151: 439 | M151: Food | N151: Series E | O151: 224 | P151: 2020 | Q151: =VLOOKUP(C151,layoffs_location!A:F,6,FALSE) -> 43.653482 | R151: =VLOOKUP(C151,layoffs_location!A:G,7,FALSE) -> -79.383935
A152: 151 | B152: VSCO | C152: Oakland | D152: =VLOOKUP(C152,layoffs_location!A:B,2,FALSE) -> San Francisco Bay Area | E152: =VLOOKUP(C152,layoffs_location!A:C,3,FALSE) -> California | F152: =VLOOKUP(C152,layoffs_location!A:D,4,FALSE) -> USA | G152: =VLOOKUP(C152,layoffs_location!A:E,5,FALSE) -> North America | H152: 45 | I152: 43935 | J152: 35 | K152: 129 | L152: 84 | M152: Consumer | N152: Series B | O152: 90 | P152: 2020 | Q152: =VLOOKUP(C152,layoffs_location!A:F,6,FALSE) -> 37.804456 | R152: =VLOOKUP(C152,layoffs_location!A:G,7,FALSE) -> -122.27136
A153: 152 | B153: Carta | C153: San Francisco | D153: =VLOOKUP(C153,layoffs_location!A:B,2,FALSE) -> San Francisco Bay Area | E153: =VLOOKUP(C153,layoffs_location!A:C,3,FALSE) -> California | F153: =VLOOKUP(C153,layoffs_location!A:D,4,FALSE) -> USA | G153: =VLOOKUP(C153,layoffs_location!A:E,5,FALSE) -> North America | H153: 161 | I153: 43936 | J153: 16 | K153: 1006 | L153: 845 | M153: Finance | N153: Series E | O153: 447 | P153: 2020 | Q153: =VLOOKUP(C153,layoffs_location!A:F,6,FALSE) -> 37.779259 | R153: =VLOOKUP(C153,layoffs_location!A:G,7,FALSE) -> -122.41933
A154: 153 | B154: GoPro | C154: San Mateo | D154: =VLOOKUP(C154,layoffs_location!A:B,2,FALSE) -> San Francisco Bay Area | E154: =VLOOKUP(C154,layoffs_location!A:C,3,FALSE) -> California | F154: =VLOOKUP(C154,layoffs_location!A:D,4,FALSE) -> USA | G154: =VLOOKUP(C154,layoffs_location!A:E,5,FALSE) -> North America | H154: 200 | I154: 43936 | J154: 20 | K154: 1000 | L154: 800 | M154: Consumer | N154: Post-IPO | O154: 288 | P154: 2020 | Q154: =VLOOKUP(C154,layoffs_location!A:F,6,FALSE) -> 37.496904 | R154: =VLOOKUP(C154,layoffs_location!A:G,7,FALSE) -> -122.33306
A155: 154 | B155: Kodiak Robotics | C155: Mountain View | D155: =VLOOKUP(C155,layoffs_location!A:B,2,FALSE) -> San Francisco Bay Area | E155: =VLOOKUP(C155,layoffs_location!A:C,3,FALSE) -> California | F155: =VLOOKUP(C155,layoffs_location!A:D,4,FALSE) -> USA | G155: =VLOOKUP(C155,layoffs_location!A:E,5,FALSE) -> North America | H155: 15 | I155: 43936 | J155: 20 | K155: 75 | L155: 60 | M155: Transportation | N155: Series A | O155: 40 | P155: 2020 | Q155: =VLOOKUP(C155,layoffs_location!A:F,6,FALSE) -> 37.389389 | R155: =VLOOKUP(C155,layoffs_location!A:G,7,FALSE) -> -122.08321
A156: 155 | B156: Opendoor | C156: San Francisco | D156: =VLOOKUP(C156,layoffs_location!A:B,2,FALSE) -> San Francisco Bay Area | E156: =VLOOKUP(C156,layoffs_location!A:C,3,FALSE) -> California | F156: =VLOOKUP(C156,layoffs_location!A:D,4,FALSE) -> USA | G156: =VLOOKUP(C156,layoffs_location!A:E,5,FALSE) -> North America | H156: 600 | I156: 43936 | J156: 35 | K156: 1714 | L156: 1114 | M156: Real Estate | N156: Series E | O156: 1500 | P156: 2020 | Q156: =VLOOKUP(C156,layoffs_location!A:F,6,FALSE) -> 37.779259 | R156: =VLOOKUP(C156,layoffs_location!A:G,7,FALSE) -> -122.41933
A157: 156 | B157: Parsable | C157: San Francisco | D157: =VLOOKUP(C157,layoffs_location!A:B,2,FALSE) -> San Francisco Bay Area | E157: =VLOOKUP(C157,layoffs_location!A:C,3,FALSE) -> California | F157: =VLOOKUP(C157,layoffs_location!A:D,4,FALSE) -> USA | G157: =VLOOKUP(C157,layoffs_location!A:E,5,FALSE) -> North America | H157: 40 | I157: 43936 | J157: 25 | K157: 160 | L157: 120 | M157: HR | N157: Series C | O157: 72 | P157: 2020 | Q157: =VLOOKUP(C157,layoffs_location!A:F,6,FALSE) -> 37.779259 | R157: =VLOOKUP(C157,layoffs_location!A:G,7,FALSE) -> -122.41933
A158: 157 | B158: Shop101 | C158: Mumbai | D158: =VLOOKUP(C158,layoffs_location!A:B,2,FALSE) -> other | E158: =VLOOKUP(C158,layoffs_location!A:C,3,FALSE) -> Maharashtra | F158: =VLOOKUP(C158,layoffs_location!A:D,4,FALSE) -> India | G158: =VLOOKUP(C158,layoffs_location!A:E,5,FALSE) -> Asia | H158: 200 | I158: 43936 | J158: 40 | K158: 500 | L158: 300 | M158: Retail | N158: Series C | O158: 19 | P158: 2020 | Q158: =VLOOKUP(C158,layoffs_location!A:F,6,FALSE) -> 19.078545 | R158: =VLOOKUP(C158,layoffs_location!A:G,7,FALSE) -> 72.878176
... A188: 187 | B188: When I Work | C188: Minneapolis | D188: =VLOOKUP(C188,layoffs_location!A:B,2,FALSE) -> other | E188: =VLOOKUP(C188,layoffs_location!A:C,3,FALSE) -> Minnesota | F188: =VLOOKUP(C188,layoffs_location!A:D,4,FALSE) -> USA | G188: =VLOOKUP(C188,layoffs_location!A:E,5,FALSE) -> North America | H188: 55 | I188: 43943 | J188: 35 | K188: 157 | L188: 102 | M188: HR | N188: Series B | O188: 24 | P188: 2020 | Q188: =VLOOKUP(C188,layoffs_location!A:F,6,FALSE) -> 44.9773 | R188: =VLOOKUP(C188,layoffs_location!A:G,7,FALSE) -> -93.265469
A189: 188 | B189: Oscar Health | C189: New York City | D189: =VLOOKUP(C189,layoffs_location!A:B,2,FALSE) -> New York | E189: =VLOOKUP(C189,layoffs_location!A:C,3,FALSE) -> New York | F189: =VLOOKUP(C189,layoffs_location!A:D,4,FALSE) -> USA | G189: =VLOOKUP(C189,layoffs_location!A:E,5,FALSE) -> North America | H189: 70 | I189: 43944 | J189: 5 | K189: 1400 | L189: 1330 | M189: Healthcare | N189: Unknown | P189: 2020 | Q189: =VLOOKUP(C189,layoffs_location!A:F,6,FALSE) -> 40.712728 | R189: =VLOOKUP(C189,layoffs_location!A:G,7,FALSE) -> -74.006015
A190: 189 | B190: Sisense | C190: New York City | D190: =VLOOKUP(C190,layoffs_location!A:B,2,FALSE) -> New York | E190: =VLOOKUP(C190,layoffs_location!A:C,3,FALSE) -> New York | F190: =VLOOKUP(C190,layoffs_location!A:D,4,FALSE) -> USA | G190: =VLOOKUP(C190,layoffs_location!A:E,5,FALSE) -> North America | H190: 80 | I190: 43944 | J190: 9 | K190: 889 | L190: 809 | M190: Data | N190: Series F | O190: 274 | P190: 2020 | Q190: =VLOOKUP(C190,layoffs_location!A:F,6,FALSE) -> 40.712728 | R190: =VLOOKUP(C190,layoffs_location!A:G,7,FALSE) -> -74.006015
A191: 190 | B191: StockX | C191: Detroit | D191: =VLOOKUP(C191,layoffs_location!A:B,2,FALSE) -> other | E191: =VLOOKUP(C191,layoffs_location!A:C,3,FALSE) -> Michigan | F191: =VLOOKUP(C191,layoffs_location!A:D,4,FALSE) -> USA | G191: =VLOOKUP(C191,layoffs_location!A:E,5,FALSE) -> North America | H191: 100 | I191: 43944 | J191: 12 | K191: 833 | L191: 733 | M191: Retail | N191: Series C | O191: 160 | P191: 2020 | Q191: =VLOOKUP(C191,layoffs_location!A:F,6,FALSE) -> 42.331551 | R191: =VLOOKUP(C191,layoffs_location!A:G,7,FALSE) -> -83.04664
A192: 191 | B192: Zenefits | C192: San Francisco | D192: =VLOOKUP(C192,layoffs_location!A:B,2,FALSE) -> San Francisco Bay Area | E192: =VLOOKUP(C192,layoffs_location!A:C,3,FALSE) -> California | F192: =VLOOKUP(C192,layoffs_location!A:D,4,FALSE) -> USA | G192: =VLOOKUP(C192,layoffs_location!A:E,5,FALSE) -> North America | H192: 87 | I192: 43944 | J192: 15 | K192: 580 | L192: 493 | M192: HR | N192: Series C | O192: 583 | P192: 2020 | Q192: =VLOOKUP(C192,layoffs_location!A:F,6,FALSE) -> 37.779259 | R192: =VLOOKUP(C192,layoffs_location!A:G,7,FALSE) -> -122.41933
A193: 192 | B193: Ada Support | C193: Toronto | D193: =VLOOKUP(C193,layoffs_location!A:B,2,FALSE) -> other | E193: =VLOOKUP(C193,layoffs_location!A:C,3,FALSE) -> Ontario | F193: =VLOOKUP(C193,layoffs_location!A:D,4,FALSE) -> Canada | G193: =VLOOKUP(C193,layoffs_location!A:E,5,FALSE) -> North America | H193: 36 | I193: 43945 | J193: 23 | K193: 157 | L193: 121 | M193: Support | N193: Series B | O193: 60 | P193: 2024 | Q193: =VLOOKUP(C193,layoffs_location!A:F,6,FALSE) -> 43.653482 | R193: =VLOOKUP(C193,layoffs_location!A:G,7,FALSE) -> -79.383935
A194: 193 | B194: Divergent 3D | C194: Los Angeles | D194: =VLOOKUP(C194,layoffs_location!A:B,2,FALSE) -> other | E194: =VLOOKUP(C194,layoffs_location!A:C,3,FALSE) -> California | F194: =VLOOKUP(C194,layoffs_location!A:D,4,FALSE) -> USA | G194: =VLOOKUP(C194,layoffs_location!A:E,5,FALSE) -> North America | H194: 57 | I194: 43945 | J194: 36 | K194: 158 | L194: 101 | M194: Transportation | N194: Series B | O194: 88 | P194: 2020 | Q194: =VLOOKUP(C194,layoffs_location!A:F,6,FALSE) -> 34.053691 | R194: =VLOOKUP(C194,layoffs_location!A:G,7,FALSE) -> -118.24277
A195: 194 | B195: Horizn Studios | C195: Berlin | D195: =VLOOKUP(C195,layoffs_location!A:B,2,FALSE) -> other | E195: =VLOOKUP(C195,layoffs_location!A:C,3,FALSE) -> Berlin | F195: =VLOOKUP(C195,layoffs_location!A:D,4,FALSE) -> Germany | G195: =VLOOKUP(C195,layoffs_location!A:E,5,FALSE) -> Europe | H195: 15 | I195: 43945 | J195: 25 | K195: 60 | L195: 45 | M195: Travel | N195: Series B | O195: 30 | P195: 2020 | Q195: =VLOOKUP(C195,layoffs_location!A:F,6,FALSE) -> 52.517037 | R195: =VLOOKUP(C195,layoffs_location!A:G,7,FALSE) -> 13.38886
A196: 195 | B196: Jiobit | C196: Chicago | D196: =VLOOKUP(C196,layoffs_location!A:B,2,FALSE) -> other | E196: =VLOOKUP(C196,layoffs_location!A:C,3,FALSE) -> Illinois | F196: =VLOOKUP(C196,layoffs_location!A:D,4,FALSE) -> USA | G196: =VLOOKUP(C196,layoffs_location!A:E,5,FALSE) -> North America | H196: 6 | I196: 43945 | J196: 21 | K196: 29 | L196: 23 | M196: Consumer | N196: Unknown | O196: 12 | P196: 2020 | Q196: =VLOOKUP(C196,layoffs_location!A:F,6,FALSE) -> 41.875562 | R196: =VLOOKUP(C196,layoffs_location!A:G,7,FALSE) -> -87.624421
A197: 196 | B197: Lighter Capital | C197: Seattle | D197: =VLOOKUP(C197,layoffs_location!A:B,2,FALSE) -> Cascadia | E197: =VLOOKUP(C197,layoffs_location!A:C,3,FALSE) -> Washington | F197: =VLOOKUP(C197,layoffs_location!A:D,4,FALSE) -> USA | G197: =VLOOKUP(C197,layoffs_location!A:E,5,FALSE) -> North America | H197: 18 | I197: 43945 | J197: 22 | K197: 82 | L197: 64 | M197: Finance | N197: Series B | O197: 15 | P197: 2020 | Q197: =VLOOKUP(C197,layoffs_location!A:F,6,FALSE) -> 47.603832 | R197: =VLOOKUP(C197,layoffs_location!A:G,7,FALSE) -> -122.33006
A198: 197 | B198: TutorMundi | C198: Sao Paulo | D198: =VLOOKUP(C198,layoffs_location!A:B,2,FALSE) -> other | E198: =VLOOKUP(C198,layoffs_location!A:C,3,FALSE) -> State of São Paulo | F198: =VLOOKUP(C198,layoffs_location!A:D,4,FALSE) -> Brazil | G198: =VLOOKUP(C198,layoffs_location!A:E,5,FALSE) -> South America | H198: 4 | I198: 43945 | J198: 100 | K198: 4 | L198: 0 | M198: Education | N198: Series A | O198: 2 | P198: 2020 | Q198: =VLOOKUP(C198,layoffs_location!A:F,6,FALSE) -> -23.550651 | R198: =VLOOKUP(C198,layoffs_location!A:G,7,FALSE) -> -46.633382
A199: 198 | B199: UPshow | C199: Chicago | D199: =VLOOKUP(C199,layoffs_location!A:B,2,FALSE) -> other | E199: =VLOOKUP(C199,layoffs_location!A:C,3,FALSE) -> Illinois | F199: =VLOOKUP(C199,layoffs_location!A:D,4,FALSE) -> USA | G199: =VLOOKUP(C199,layoffs_location!A:E,5,FALSE) -> North America | H199: 19 | I199: 43945 | J199: 30 | K199: 63 | L199: 44 | M199: Marketing | N199: Series A | O199: 7 | P199: 2020 | Q199: =VLOOKUP(C199,layoffs_location!A:F,6,FALSE) -> 41.875562 | R199: =VLOOKUP(C199,layoffs_location!A:G,7,FALSE) -> -87.624421
A200: 199 | B200: Welkin Health | C200: San Francisco | D200: =VLOOKUP(C200,layoffs_location!A:B,2,FALSE) -> San Francisco Bay Area | E200: =VLOOKUP(C200,layoffs_location!A:C,3,FALSE) -> California | F200: =VLOOKUP(C200,layoffs_location!A:D,4,FALSE) -> USA | G200: =VLOOKUP(C200,layoffs_location!A:E,5,FALSE) -> North America | H200: 10 | I200: 43945 | J200: 33 | K200: 30 | L200: 20 | M200: Healthcare | N200: Series B | O200: 29 | P200: 2020 | Q200: =VLOOKUP(C200,layoffs_location!A:F,6,FALSE) -> 37.779259 | R200: =VLOOKUP(C200,layoffs_location!A:G,7,FALSE) -> -122.41933
A201: 200 | B201: Submittable | C201: Missoula | D201: =VLOOKUP(C201,layoffs_location!A:B,2,FALSE) -> other | E201: =VLOOKUP(C201,layoffs_location!A:C,3,FALSE) -> Montana | F201: =VLOOKUP(C201,layoffs_location!A:D,4,FALSE) -> USA | G201: =VLOOKUP(C201,layoffs_location!A:E,5,FALSE) -> North America | H201: 30 | I201: 43946 | J201: 20 | K201: 150 | L201: 120 | M201: Other | N201: Series B | O201: 17 | P201: 2020 | Q201: =VLOOKUP(C201,layoffs_location!A:F,6,FALSE) -> 46.870105 | R201: =VLOOKUP(C201,layoffs_location!A:G,7,FALSE) -> -113.99527
... A292: 291 | B292: SynapseFI | C292: San Francisco | D292: =VLOOKUP(C292,layoffs_location!A:B,2,FALSE) -> San Francisco Bay Area | E292: =VLOOKUP(C292,layoffs_location!A:C,3,FALSE) -> California | F292: =VLOOKUP(C292,layoffs_location!A:D,4,FALSE) -> USA | G292: =VLOOKUP(C292,layoffs_location!A:E,5,FALSE) -> North America | H292: 63 | I292: 43994 | J292: 48 | K292: 131 | L292: 68 | M292: Finance | N292: Series B | O292: 50 | P292: 2020 | Q292: =VLOOKUP(C292,layoffs_location!A:F,6,FALSE) -> 37.779259 | R292: =VLOOKUP(C292,layoffs_location!A:G,7,FALSE) -> -122.41933
A293: 292 | B293: Uber | C293: Amsterdam | D293: =VLOOKUP(C293,layoffs_location!A:B,2,FALSE) -> other | E293: =VLOOKUP(C293,layoffs_location!A:C,3,FALSE) -> non | F293: =VLOOKUP(C293,layoffs_location!A:D,4,FALSE) -> Netherlands | G293: =VLOOKUP(C293,layoffs_location!A:E,5,FALSE) -> Europe | H293: 225 | I293: 43994 | J293: 25 | K293: 900 | L293: 675 | M293: Transportation | N293: Post-IPO | P293: 2020 | Q293: =VLOOKUP(C293,layoffs_location!A:F,6,FALSE) -> 52.37308 | R293: =VLOOKUP(C293,layoffs_location!A:G,7,FALSE) -> 4.8924534
A294: 293 | B294: Grab | C294: Singapore | D294: =VLOOKUP(C294,layoffs_location!A:B,2,FALSE) -> other | E294: =VLOOKUP(C294,layoffs_location!A:C,3,FALSE) -> non | F294: =VLOOKUP(C294,layoffs_location!A:D,4,FALSE) -> Singapore | G294: =VLOOKUP(C294,layoffs_location!A:E,5,FALSE) -> Asia | H294: 360 | I294: 43998 | J294: 5 | K294: 7200 | L294: 6840 | M294: Transportation | N294: Series I | P294: 2020 | Q294: =VLOOKUP(C294,layoffs_location!A:F,6,FALSE) -> 1.2899175 | R294: =VLOOKUP(C294,layoffs_location!A:G,7,FALSE) -> 103.85191
A295: 294 | B295: PaisaBazaar | C295: Gurugram | D295: =VLOOKUP(C295,layoffs_location!A:B,2,FALSE) -> other | E295: =VLOOKUP(C295,layoffs_location!A:C,3,FALSE) -> Haryana | F295: =VLOOKUP(C295,layoffs_location!A:D,4,FALSE) -> India | G295: =VLOOKUP(C295,layoffs_location!A:E,5,FALSE) -> Asia | H295: 1500 | I295: 43998 | J295: 50 | K295: 3000 | L295: 1500 | M295: Finance | N295: Series G | O295: 496 | P295: 2020 | Q295: =VLOOKUP(C295,layoffs_location!A:F,6,FALSE) -> 28.464615 | R295: =VLOOKUP(C295,layoffs_location!A:G,7,FALSE) -> 77.029919
A296: 295 | B296: Redox | C296: Madison | D296: =VLOOKUP(C296,layoffs_location!A:B,2,FALSE) -> other | E296: =VLOOKUP(C296,layoffs_location!A:C,3,FALSE) -> Wisconsin | F296: =VLOOKUP(C296,layoffs_location!A:D,4,FALSE) -> USA | G296: =VLOOKUP(C296,layoffs_location!A:E,5,FALSE) -> North America | H296: 44 | I296: 43998 | J296: 25 | K296: 176 | L296: 132 | M296: Healthcare | N296: Series C | O296: 50 | P296: 2020 | Q296: =VLOOKUP(C296,layoffs_location!A:F,6,FALSE) -> 43.074761 | R296: =VLOOKUP(C296,layoffs_location!A:G,7,FALSE) -> -89.383761
A297: 296 | B297: Splunk | C297: San Jose | D297: =VLOOKUP(C297,layoffs_location!A:B,2,FALSE) -> San Francisco Bay Area | E297: =VLOOKUP(C297,layoffs_location!A:C,3,FALSE) -> California | F297: =VLOOKUP(C297,layoffs_location!A:D,4,FALSE) -> USA | G297: =VLOOKUP(C297,layoffs_location!A:E,5,FALSE) -> North America | H297: 70 | I297: 43998 | J297: 1 | K297: 7000 | L297: 6930 | M297: Data | N297: Post-IPO | O297: 40 | P297: 2020 | Q297: =VLOOKUP(C297,layoffs_location!A:F,6,FALSE) -> 37.336166 | R297: =VLOOKUP(C297,layoffs_location!A:G,7,FALSE) -> -121.89059
A298: 297 | B298: Navi | C298: Bengaluru | D298: =VLOOKUP(C298,layoffs_location!A:B,2,FALSE) -> other | E298: =VLOOKUP(C298,layoffs_location!A:C,3,FALSE) -> Karnataka | F298: =VLOOKUP(C298,layoffs_location!A:D,4,FALSE) -> India | G298: =VLOOKUP(C298,layoffs_location!A:E,5,FALSE) -> Asia | H298: 40 | I298: 43999 | J298: 25 | K298: 160 | L298: 120 | M298: Finance | N298: Private Equity | O298: 582 | P298: 2020 | Q298: =VLOOKUP(C298,layoffs_location!A:F,6,FALSE) -> 12.988157 | R298: =VLOOKUP(C298,layoffs_location!A:G,7,FALSE) -> 77.6226
A299: 298 | B299: Intuit | C299: Mountain View | D299: =VLOOKUP(C299,layoffs_location!A:B,2,FALSE) -> San Francisco Bay Area | E299: =VLOOKUP(C299,layoffs_location!A:C,3,FALSE) -> California | F299: =VLOOKUP(C299,layoffs_location!A:D,4,FALSE) -> USA | G299: =VLOOKUP(C299,layoffs_location!A:E,5,FALSE) -> North America | H299: 715 | I299: 44004 | J299: 7 | K299: 10214 | L299: 9499 | M299: Finance | N299: Post-IPO | O299: 18 | P299: 2020 | Q299: =VLOOKUP(C299,layoffs_location!A:F,6,FALSE) -> 37.389389 | R299: =VLOOKUP(C299,layoffs_location!A:G,7,FALSE) -> -122.08321
A300: 299 | B300: Dark | C300: San Francisco | D300: =VLOOKUP(C300,layoffs_location!A:B,2,FALSE) -> San Francisco Bay Area | E300: =VLOOKUP(C300,layoffs_location!A:C,3,FALSE) -> California | F300: =VLOOKUP(C300,layoffs_location!A:D,4,FALSE) -> USA | G300: =VLOOKUP(C300,layoffs_location!A:E,5,FALSE) -> North America | H300: 6 | I300: 44005 | J300: 100 | K300: 6 | L300: 0 | M300: Product | N300: Seed | O300: 3 | P300: 2020 | Q300: =VLOOKUP(C300,layoffs_location!A:F,6,FALSE) -> 37.779259 | R300: =VLOOKUP(C300,layoffs_location!A:G,7,FALSE) -> -122.41933
A301: 300 | B301: Gojek | C301: Jakarta | D301: =VLOOKUP(C301,layoffs_location!A:B,2,FALSE) -> other | E301: =VLOOKUP(C301,layoffs_location!A:C,3,FALSE) -> non | F301: =VLOOKUP(C301,layoffs_location!A:D,4,FALSE) -> Indonesia | G301: =VLOOKUP(C301,layoffs_location!A:E,5,FALSE) -> Asia | H301: 430 | I301: 44005 | J301: 9 | K301: 4778 | L301: 4348 | M301: Transportation | N301: Series F | O301: 4800 | P301: 2020 | Q301: =VLOOKUP(C301,layoffs_location!A:F,6,FALSE) -> -6.175247 | R301: =VLOOKUP(C301,layoffs_location!A:G,7,FALSE) -> 106.82705
A302: 301 | B302: ScaleFactor | C302: Austin | D302: =VLOOKUP(C302,layoffs_location!A:B,2,FALSE) -> other | E302: =VLOOKUP(C302,layoffs_location!A:C,3,FALSE) -> Texas | F302: =VLOOKUP(C302,layoffs_location!A:D,4,FALSE) -> USA | G302: =VLOOKUP(C302,layoffs_location!A:E,5,FALSE) -> North America | H302: 90 | I302: 44005 | J302: 90 | K302: 100 | L302: 10 | M302: Finance | N302: Series C | O302: 103 | P302: 2020 | Q302: =VLOOKUP(C302,layoffs_location!A:F,6,FALSE) -> 30.271129 | R302: =VLOOKUP(C302,layoffs_location!A:G,7,FALSE) -> -97.7437
A303: 302 | B303: Sonos | C303: New York City | D303: =VLOOKUP(C303,layoffs_location!A:B,2,FALSE) -> New York | E303: =VLOOKUP(C303,layoffs_location!A:C,3,FALSE) -> New York | F303: =VLOOKUP(C303,layoffs_location!A:D,4,FALSE) -> USA | G303: =VLOOKUP(C303,layoffs_location!A:E,5,FALSE) -> North America | H303: 174 | I303: 44006 | J303: 12 | K303: 1450 | L303: 1276 | M303: Consumer | N303: Post-IPO | O303: 455 | P303: 2020 | Q303: =VLOOKUP(C303,layoffs_location!A:F,6,FALSE) -> 40.712728 | R303: =VLOOKUP(C303,layoffs_location!A:G,7,FALSE) -> -74.006015
A304: 303 | B304: Bounce | C304: Bengaluru | D304: =VLOOKUP(C304,layoffs_location!A:B,2,FALSE) -> other | E304: =VLOOKUP(C304,layoffs_location!A:C,3,FALSE) -> Karnataka | F304: =VLOOKUP(C304,layoffs_location!A:D,4,FALSE) -> India | G304: =VLOOKUP(C304,layoffs_location!A:E,5,FALSE) -> Asia | H304: 130 | I304: 44011 | J304: 22 | K304: 591 | L304: 461 | M304: Transportation | N304: Series D | O304: 214 | P304: 2020 | Q304: =VLOOKUP(C304,layoffs_location!A:F,6,FALSE) -> 12.988157 | R304: =VLOOKUP(C304,layoffs_location!A:G,7,FALSE) -> 77.6226
A305: 304 | B305: Katerra | C305: Menlo Park | D305: =VLOOKUP(C305,layoffs_location!A:B,2,FALSE) -> San Francisco Bay Area | E305: =VLOOKUP(C305,layoffs_location!A:C,3,FALSE) -> California | F305: =VLOOKUP(C305,layoffs_location!A:D,4,FALSE) -> USA | G305: =VLOOKUP(C305,layoffs_location!A:E,5,FALSE) -> North America | H305: 400 | I305: 44011 | J305: 7 | K305: 5714 | L305: 5314 | M305: Construction | N305: Series E | O305: 1300 | P305: 2020 | Q305: =VLOOKUP(C305,layoffs_location!A:F,6,FALSE) -> 37.451967 | R305: =VLOOKUP(C305,layoffs_location!A:G,7,FALSE) -> -122.17799
A306: 305 | B306: G2 | C306: Chicago | D306: =VLOOKUP(C306,layoffs_location!A:B,2,FALSE) -> other | E306: =VLOOKUP(C306,layoffs_location!A:C,3,FALSE) -> Illinois | F306: =VLOOKUP(C306,layoffs_location!A:D,4,FALSE) -> USA | G306: =VLOOKUP(C306,layoffs_location!A:E,5,FALSE) -> North America | H306: 17 | I306: 44012 | J306: 5 | K306: 340 | L306: 323 | M306: Marketing | N306: Series C | O306: 101 | P306: 2020 | Q306: =VLOOKUP(C306,layoffs_location!A:F,6,FALSE) -> 41.875562 | R306: =VLOOKUP(C306,layoffs_location!A:G,7,FALSE) -> -87.624421
... A346: 345 | B346: Better.com | C346: New York City | D346: =VLOOKUP(C346,layoffs_location!A:B,2,FALSE) -> New York | E346: =VLOOKUP(C346,layoffs_location!A:C,3,FALSE) -> New York | F346: =VLOOKUP(C346,layoffs_location!A:D,4,FALSE) -> USA | G346: =VLOOKUP(C346,layoffs_location!A:E,5,FALSE) -> North America | H346: 900 | I346: 44531 | J346: 9 | K346: 10000 | L346: 9100 | M346: Real Estate | N346: Unknown | O346: 905 | P346: 2021 | Q346: =VLOOKUP(C346,layoffs_location!A:F,6,FALSE) -> 40.712728 | R346: =VLOOKUP(C346,layoffs_location!A:G,7,FALSE) -> -74.006015
A347: 346 | B347: Delivery Hero | C347: Berlin | D347: =VLOOKUP(C347,layoffs_location!A:B,2,FALSE) -> other | E347: =VLOOKUP(C347,layoffs_location!A:C,3,FALSE) -> Berlin | F347: =VLOOKUP(C347,layoffs_location!A:D,4,FALSE) -> Germany | G347: =VLOOKUP(C347,layoffs_location!A:E,5,FALSE) -> Europe | H347: 300 | I347: 44552 | J347: 6.9767442 | K347: 4300 | L347: 4000 | M347: Food | N347: Post-IPO | P347: 2021 | Q347: =VLOOKUP(C347,layoffs_location!A:F,6,FALSE) -> 52.517037 | R347: =VLOOKUP(C347,layoffs_location!A:G,7,FALSE) -> 13.38886
A348: 347 | B348: Glossier | C348: New York City | D348: =VLOOKUP(C348,layoffs_location!A:B,2,FALSE) -> New York | E348: =VLOOKUP(C348,layoffs_location!A:C,3,FALSE) -> New York | F348: =VLOOKUP(C348,layoffs_location!A:D,4,FALSE) -> USA | G348: =VLOOKUP(C348,layoffs_location!A:E,5,FALSE) -> North America | H348: 80 | I348: 44587 | J348: 33 | K348: 242 | L348: 162 | M348: Consumer | N348: Series E | O348: 266 | P348: 2022 | Q348: =VLOOKUP(C348,layoffs_location!A:F,6,FALSE) -> 40.712728 | R348: =VLOOKUP(C348,layoffs_location!A:G,7,FALSE) -> -74.006015
A349: 348 | B349: Gopuff | C349: Philadelphia | D349: =VLOOKUP(C349,layoffs_location!A:B,2,FALSE) -> other | E349: =VLOOKUP(C349,layoffs_location!A:C,3,FALSE) -> Pennsylvania | F349: =VLOOKUP(C349,layoffs_location!A:D,4,FALSE) -> USA | G349: =VLOOKUP(C349,layoffs_location!A:E,5,FALSE) -> North America | H349: 100 | I349: 44587 | J349: 0.66225166 | K349: 15100 | L349: 15000 | M349: Food | N349: Series H | O349: 3400 | P349: 2022 | Q349: =VLOOKUP(C349,layoffs_location!A:F,6,FALSE) -> 39.952724 | R349: =VLOOKUP(C349,layoffs_location!A:G,7,FALSE) -> -75.163526
A350: 349 | B350: Rhino | C350: New York City | D350: =VLOOKUP(C350,layoffs_location!A:B,2,FALSE) -> New York | E350: =VLOOKUP(C350,layoffs_location!A:C,3,FALSE) -> New York | F350: =VLOOKUP(C350,layoffs_location!A:D,4,FALSE) -> USA | G350: =VLOOKUP(C350,layoffs_location!A:E,5,FALSE) -> North America | H350: 57 | I350: 44595 | J350: 20 | K350: 285 | L350: 228 | M350: Real Estate | N350: Unknown | O350: 133 | P350: 2022 | Q350: =VLOOKUP(C350,layoffs_location!A:F,6,FALSE) -> 40.712728 | R350: =VLOOKUP(C350,layoffs_location!A:G,7,FALSE) -> -74.006015
A351: 350 | B351: Peloton | C351: New York City | D351: =VLOOKUP(C351,layoffs_location!A:B,2,FALSE) -> New York | E351: =VLOOKUP(C351,layoffs_location!A:C,3,FALSE) -> New York | F351: =VLOOKUP(C351,layoffs_location!A:D,4,FALSE) -> USA | G351: =VLOOKUP(C351,layoffs_location!A:E,5,FALSE) -> North America | H351: 2800 | I351: 44600 | J351: 20 | K351: 14000 | L351: 11200 | M351: Fitness | N351: Post-IPO | O351: 1900 | P351: 2022 | Q351: =VLOOKUP(C351,layoffs_location!A:F,6,FALSE) -> 40.712728 | R351: =VLOOKUP(C351,layoffs_location!A:G,7,FALSE) -> -74.006015
A352: 351 | B352: Daily Harvest | C352: New York City | D352: =VLOOKUP(C352,layoffs_location!A:B,2,FALSE) -> New York | E352: =VLOOKUP(C352,layoffs_location!A:C,3,FALSE) -> New York | F352: =VLOOKUP(C352,layoffs_location!A:D,4,FALSE) -> USA | G352: =VLOOKUP(C352,layoffs_location!A:E,5,FALSE) -> North America | H352: 60 | I352: 44602 | J352: 20 | K352: 300 | L352: 240 | M352: Food | N352: Series D | O352: 120 | P352: 2022 | Q352: =VLOOKUP(C352,layoffs_location!A:F,6,FALSE) -> 40.712728 | R352: =VLOOKUP(C352,layoffs_location!A:G,7,FALSE) -> -74.006015
A353: 352 | B353: Hopin | C353: London | D353: =VLOOKUP(C353,layoffs_location!A:B,2,FALSE) -> other | E353: =VLOOKUP(C353,layoffs_location!A:C,3,FALSE) -> England | F353: =VLOOKUP(C353,layoffs_location!A:D,4,FALSE) -> UK | G353: =VLOOKUP(C353,layoffs_location!A:E,5,FALSE) -> Europe | H353: 138 | I353: 44602 | J353: 12 | K353: 1150 | L353: 1012 | M353: Other | N353: Series D | O353: 1000 | P353: 2022 | Q353: =VLOOKUP(C353,layoffs_location!A:F,6,FALSE) -> 51.489334 | R353: =VLOOKUP(C353,layoffs_location!A:G,7,FALSE) -> -0.14405508
A354: 353 | B354: Homie | C354: Salt Lake City | D354: =VLOOKUP(C354,layoffs_location!A:B,2,FALSE) -> other | E354: =VLOOKUP(C354,layoffs_location!A:C,3,FALSE) -> Utah | F354: =VLOOKUP(C354,layoffs_location!A:D,4,FALSE) -> USA | G354: =VLOOKUP(C354,layoffs_location!A:E,5,FALSE) -> North America | H354: 119 | I354: 44606 | J354: 29 | K354: 410 | L354: 291 | M354: Real Estate | N354: Series B | O354: 35 | P354: 2022 | Q354: =VLOOKUP(C354,layoffs_location!A:F,6,FALSE) -> 40.75962 | R354: =VLOOKUP(C354,layoffs_location!A:G,7,FALSE) -> -111.8868
A355: 354 | B355: Liv Up | C355: Sao Paulo | D355: =VLOOKUP(C355,layoffs_location!A:B,2,FALSE) -> other | E355: =VLOOKUP(C355,layoffs_location!A:C,3,FALSE) -> State of São Paulo | F355: =VLOOKUP(C355,layoffs_location!A:D,4,FALSE) -> Brazil | G355: =VLOOKUP(C355,layoffs_location!A:E,5,FALSE) -> South America | H355: 100 | I355: 44608 | J355: 15 | K355: 667 | L355: 567 | M355: Food | N355: Series D | O355: 118 | P355: 2022 | Q355: =VLOOKUP(C355,layoffs_location!A:F,6,FALSE) -> -23.550651 | R355: =VLOOKUP(C355,layoffs_location!A:G,7,FALSE) -> -46.633382
A356: 355 | B356: Virgin Hyperloop | C356: Los Angeles | D356: =VLOOKUP(C356,layoffs_location!A:B,2,FALSE) -> other | E356: =VLOOKUP(C356,layoffs_location!A:C,3,FALSE) -> California | F356: =VLOOKUP(C356,layoffs_location!A:D,4,FALSE) -> USA | G356: =VLOOKUP(C356,layoffs_location!A:E,5,FALSE) -> North America | H356: 111 | I356: 44613 | J356: 50 | K356: 222 | L356: 111 | M356: Transportation | N356: Unknown | O356: 368 | P356: 2022 | Q356: =VLOOKUP(C356,layoffs_location!A:F,6,FALSE) -> 34.053691 | R356: =VLOOKUP(C356,layoffs_location!A:G,7,FALSE) -> -118.24277
A357: 356 | B357: Wish | C357: San Francisco | D357: =VLOOKUP(C357,layoffs_location!A:B,2,FALSE) -> San Francisco Bay Area | E357: =VLOOKUP(C357,layoffs_location!A:C,3,FALSE) -> California | F357: =VLOOKUP(C357,layoffs_location!A:D,4,FALSE) -> USA | G357: =VLOOKUP(C357,layoffs_location!A:E,5,FALSE) -> North America | H357: 190 | I357: 44621 | J357: 15 | K357: 1267 | L357: 1077 | M357: Retail | N357: Post-IPO | O357: 1600 | P357: 2022 | Q357: =VLOOKUP(C357,layoffs_location!A:F,6,FALSE) -> 37.779259 | R357: =VLOOKUP(C357,layoffs_location!A:G,7,FALSE) -> -122.41933
A358: 357 | B358: Hyperscience | C358: New York City | D358: =VLOOKUP(C358,layoffs_location!A:B,2,FALSE) -> New York | E358: =VLOOKUP(C358,layoffs_location!A:C,3,FALSE) -> New York | F358: =VLOOKUP(C358,layoffs_location!A:D,4,FALSE) -> USA | G358: =VLOOKUP(C358,layoffs_location!A:E,5,FALSE) -> North America | H358: 100 | I358: 44623 | J358: 25 | K358: 400 | L358: 300 | M358: Data | N358: Series E | O358: 289 | P358: 2022 | Q358: =VLOOKUP(C358,layoffs_location!A:F,6,FALSE) -> 40.712728 | R358: =VLOOKUP(C358,layoffs_location!A:G,7,FALSE) -> -74.006015
A359: 358 | B359: Adaptive Biotechnology | C359: Seattle | D359: =VLOOKUP(C359,layoffs_location!A:B,2,FALSE) -> Cascadia | E359: =VLOOKUP(C359,layoffs_location!A:C,3,FALSE) -> Washington | F359: =VLOOKUP(C359,layoffs_location!A:D,4,FALSE) -> USA | G359: =VLOOKUP(C359,layoffs_location!A:E,5,FALSE) -> North America | H359: 100 | I359: 44628 | J359: 12 | K359: 833 | L359: 733 | M359: Healthcare | N359: Post-IPO | O359: 406 | P359: 2022 | Q359: =VLOOKUP(C359,layoffs_location!A:F,6,FALSE) -> 47.603832 | R359: =VLOOKUP(C359,layoffs_location!A:G,7,FALSE) -> -122.33006
... A385: 384 | B385: Vedantu | C385: Bengaluru | D385: =VLOOKUP(C385,layoffs_location!A:B,2,FALSE) -> other | E385: =VLOOKUP(C385,layoffs_location!A:C,3,FALSE) -> Karnataka | F385: =VLOOKUP(C385,layoffs_location!A:D,4,FALSE) -> India | G385: =VLOOKUP(C385,layoffs_location!A:E,5,FALSE) -> Asia | H385: 200 | I385: 44686 | J385: 3 | K385: 6667 | L385: 6467 | M385: Education | N385: Series E | O385: 292 | P385: 2022 | Q385: =VLOOKUP(C385,layoffs_location!A:F,6,FALSE) -> 12.988157 | R385: =VLOOKUP(C385,layoffs_location!A:G,7,FALSE) -> 77.6226
A386: 385 | B386: Reef | C386: Miami | D386: =VLOOKUP(C386,layoffs_location!A:B,2,FALSE) -> other | E386: =VLOOKUP(C386,layoffs_location!A:C,3,FALSE) -> Florida | F386: =VLOOKUP(C386,layoffs_location!A:D,4,FALSE) -> USA | G386: =VLOOKUP(C386,layoffs_location!A:E,5,FALSE) -> North America | H386: 750 | I386: 44687 | J386: 5 | K386: 15000 | L386: 14250 | M386: Transportation | N386: Unknown | P386: 2022 | Q386: =VLOOKUP(C386,layoffs_location!A:F,6,FALSE) -> 25.774173 | R386: =VLOOKUP(C386,layoffs_location!A:G,7,FALSE) -> -80.19362
...

Sheet layoffs_location
A1: location_HQ | B1: Region | C1: State | D1: Country | E1: Continent | F1: latitude | G1: longitude
A2: Adelaide | B2: other | C2: South Australia | D2: Australia | E2: Oceana | F2: -34.928181 | G2: 138.59993
A3: Agoura Hills | B3: other | C3: California | D3: USA | E3: North America | F3: 34.14791 | G3: -118.7657
A4: Ahmedabad | B4: other | C4: Gujarat | D4: India | E4: Asia | F4: 23.021624 | G4: 72.579707
A5: Alameda | B5: San Francisco Bay Area | C5: California | D5: USA | E5: North America | F5: 37.609029 | G5: -121.89914
A6: Amsterdam | B6: other | C6: non | D6: Netherlands | E6: Europe | F6: 52.37308 | G6: 4.8924534
A7: Ann Arbor | B7: other | C7: Michigan | D7: USA | E7: North America | F7: 42.281372 | G7: -83.748462
A8: Arlington | B8: other | C8: Texas | D8: USA | E8: North America | F8: 32.729131 | G8: -97.110122
A9: Atlanta | B9: other | C9: Georgia | D9: USA | E9: North America | F9: 33.748992 | G9: -84.390264
A10: Auckland | B10: other | C10: non | D10: New Zealand | E10: Oceana | F10: -36.852095 | G10: 174.76318
A11: Austin | B11: other | C11: Texas | D11: USA | E11: North America | F11: 30.271129 | G11: -97.7437
A12: Baltimore | B12: other | C12: Maryland | D12: USA | E12: North America | F12: 39.290882 | G12: -76.610759
A13: Bangkok | B13: other | C13: non | D13: Thailand | E13: Asia | F13: 13.752494 | G13: 100.49351
... A248: Walldorf | B248: other | C248: Baden-Würtemberg | D248: Germany | E248: Europe | F248: 49.303813 | G248: 8.6433518
A249: Walnut | B249: San Francisco Bay Area | C249: California | D249: USA | E249: North America | F249: 37,910076 | G249: -122.06519
A250: Walnut Creek | B250: San Francisco Bay Area | C250: California | D250: USA | E250: North America | F250: 37.910076 | G250: -122.06519
A251: Waltham | B251: other | C251: Massachusetts | D251: USA | E251: North America | F251: 42.37564 | G251: -71.2358
A252: Warsaw | B252: other | C252: non | D252: Poland | E252: Europe | F252: 52.233717 | G252: 21.071432
A253: Washington DC | B253: other | C253: District of Columbia | D253: USA | E253: North America | F253: 38.895037 | G253: -77.036543
A254: Waterloo | B254: other | C254: Ontario | D254: Canada | E254: North America | F254: 43.46527 | G254: -80.522296
A255: Wellington | B255: other | C255: non | D255: New Zealand | E255: Oceana | F255: -41.288795 | G255: 174.77721
A256: Wilmington | B256: other | C256: Delaware | D256: USA | E256: North America | F256: 39.745947 | G256: -75.546589
A257: Winnipeg | B257: other | C257: Manitoba | D257: Canada | E257: North America | F257: 49.895077 | G257: -97.138451
A258: Xi'an | B258: other | C258: non | D258: China | E258: Asia | F258: 34.261004 | G258: 108.94234
A259: Yavne | B259: other | C259: non | D259: Israel | E259: Asia | F259: 31.876886 | G259: 34.738297
A260: Zephyr Cove | B260: other | C260: Nevada | D260: USA | E260: North America | F260: 39.002873 | G260: -119.93738
A261: Zurich | B261: other | C261: non | D261: Switzerland | E261: Europe | F261: 47.374449 | G261: 8.5410422

Sheet companies
A1: company-name | B1: company-code | C1: Emplyees_202601 | D1: Country
A2: Amazon | B2: AMZN | C2: 1546000 | D2: USA
A3: Jingdong Mall | B3: JD | C3: 900000 | D3: China
A4: Foxconn | B4: 2317.TW | C4: 826608 | D4: Taiwan
A5: IBM | B5: IBM | C5: 270300 | D5: USA
A6: Microsoft | B6: MSFT | C6: 228000 | D6: USA
A7: Panasonic | B7: 6752.T | C7: 207548 | D7: Japan
A8: Google | B8: GOOG | C8: 187103 | D8: USA
A9: Oracle | B9: ORCL | C9: 162000 | D9: USA
A10: Schneider Electric | B10: SU.PA | C10: 155822 | D10: France
A11: Apple | B11: AAPL | C11: 150000 | D11: USA
A12: Genpact | B12: G | C12: 146000 | D12: Bermuda
A13: Tesla | B13: TSLA | C13: 125665 | D13: USA
... A565: D2L Inc. | B565: DTOL.TO | C565: 1000 | D565: Canada
A566: Upland Software | B566: UPLD | C566: 998 | D566: USA
A567: SAKURA Internet | B567: 3778.T | C567: 997 | D567: Japan
A568: WithSecure Oyj | B568: WITH.HE | C568: 993 | D568: Finland
A569: Appen | B569: APX.AX | C569: 992 | D569: Australia
A570: Docebo | B570: DCBO | C570: 991 | D570: Canada
A571: Trainline | B571: TRN.L | C571: 990 | D571: UK
A572: Trustpilot Group | B572: TRST.L | C572: 988 | D572: Denmark
A573: Quick Heal | B573: QUICKHEAL.NS | C573: 986 | D573: India
A574: Zip Co | B574: ZIP.AX | C574: 985 | D574: Australia
A575: Cambricon Technologies | B575: 688256.SS | C575: 980 | D575: China
A576: PEXA Group | B576: PXA.AX | C576: 968 | D576: Australia
A577: LegalZoom | B577: LZ | C577: 964 | D577: USA
... A1004: Sphere 3D | B1004: ANY | C1004: 2 | D1004: Canada
A1005: Sonatype | B1005: =VLOOKUP(A1005,[1]StockPrice!$C:$D,2,FALSE) -> #N/A
A1006: Redbubble | B1006: =VLOOKUP(A1006,[1]StockPrice!$C:$D,2,FALSE) -> #N/A
A1007: Cornershop | B1007: =VLOOKUP(A1007,[1]StockPrice!$C:$D,2,FALSE) -> #N/A
A1008: Happay | B1008: =VLOOKUP(A1008,[1]StockPrice!$C:$D,2,FALSE) -> #N/A
A1009: Lemonade | B1009: =VLOOKUP(A1009,[1]StockPrice!$C:$D,2,FALSE) -> 39.8946
A1010: Zepz | B1010: =VLOOKUP(A1010,[1]StockPrice!$C:$D,2,FALSE) -> #N/A
A1011: Pie Insurance | B1011: =VLOOKUP(A1011,[1]StockPrice!$C:$D,2,FALSE) -> #N/A
A1012: Guild | B1012: =VLOOKUP(A1012,[1]StockPrice!$C:$D,2,FALSE) -> #N/A
A1013: Western Digital | B1013: =VLOOKUP(A1013,[1]StockPrice!$C:$D,2,FALSE) -> 10.8611
A1014: Airmeet | B1014: =VLOOKUP(A1014,[1]StockPrice!$C:$D,2,FALSE) -> #N/A
A1015: Evolve | B1015: =VLOOKUP(A1015,[1]StockPrice!$C:$D,2,FALSE) -> #N/A
A1016: Taxfix | B1016: =VLOOKUP(A1016,[1]StockPrice!$C:$D,2,FALSE) -> #N/A
... A1400: Priceline | B1400: =VLOOKUP(A1400,[1]StockPrice!$C:$D,2,FALSE) -> #N/A
A1401: 0 | B1401: =VLOOKUP(A1401,[1]StockPrice!$C:$D,2,FALSE) -> #N/A
